{
    "qna": [
        {
            "for_column": "age",
            "question"  : "Εισάγετε την ηλικία του ασθενούς:",
            "answers"   : []
        },
        {
            "for_column": "Male",
            "question"  : "Επιλέξετε το φύλο του ασθενούς:",
            "answers"   : [
                            {
                                "shown_value": "Male",
                                "actual_value": "True"
                            }, 
                            {
                                "shown_value": "Female",
                                "actual_value": "False"
                            }
                        ]
        },
        {
            "for_column": "Chest pain type",
            "question"  : "Ο ασθενής έχει στηθάγχη:",
            "answers"   : [
                            {
                                "shown_value": "Ασυμπτωματική",
                                "actual_value": 1
                            },
                            {
                                "shown_value": "Ασταθή",
                                "actual_value": 2
                            },
                            {
                                "shown_value": "Σταθερή", 
                                "actual_value": 3
                            },
                            {
                                "shown_value": "Δεν έχει στηθάγχη",
                                "actual_value": 4
                            }
                        ]
        },
        {
            "for_column": "trestbps",
            "question"  : "Πόσους καρδιακούς παλμούς ανά λεπτό έχει ο ασθενής σε κατάσταση ξεκούρασης;",
            "answers"   : []
        },
        {
            "for_column": "cholesterol",
            "question"  : "Ποια ήταν τα επίπεδα χοληστερόλης του ασθενούς στις τελευταίες αιματολιγικές εξετάσεις;",
            "answers"   : []
        },
        {
            "for_column": "fasting blood sugar",
            "question"  : "Τα επίπεδα σακχάρου του ασθενούς σε κατάσταση νηστείας είναι πάνω από 120mg/dl:",
            "answers"   : [
                                {
                                    "shown_value": "Ναι",
                                    "actual_value": "True"
                                }, 
                                {
                                    "shown_value": "Όχι",
                                    "actual_value": "False"
                                }
                            ]
        },
        {
            "for_column": "resting ecg",
            "question"  : "Ποιο ήταν το αποτέλεσμα του τελευταίου ηλεκτροκαρδιαγραφήματος του ασθενούς;",
            "answers"   : [
                                {
                                    "shown_value": "Φυσιολογικό",
                                    "actual_value": "0"
                                }, 
                                {
                                    "shown_value": "Ανύψωση του ST",
                                    "actual_value": "1"
                                },
                                {
                                    "shown_value": "Άλλο",
                                    "actual_value": "2"
                                }
                            ]
        },
        {
            "for_column": "max heart rate",
            "question"  : "Ποιοι ήταν οι μέγιστοι καρδιακοί παλμοί του ασθενούς στο τελευταίο τεστ κοπώσεως;",
            "answers"   : []
        },
        {
            "for_column": "exercise angina",
            "question"  : "Ο ασθενής αισθάνεται πόνους στο στήθος κατα τη διάρκεια της άσκησης;",
            "answers"   : [
                                {
                                    "shown_value": "Ναι",
                                    "actual_value": "True"
                                }, 
                                {
                                    "shown_value": "Όχι",
                                    "actual_value": "False"
                                }
                            ]
        },
        {
            "for_column": "oldpeak",
            "question"  : "Πόσα χιλιοστά ήταν η υποχώρηση του ST τμήματος του ασθενούς σε σχέση με το αντίστοιχο σε κατάσταση ξεκούρασης (oldpeak) στο τελευταίο του τεστ κοπώσεως;",
            "answers"   : []
        }
    ]

}